margin_strategy_sdk/__init__.py
margin_strategy_sdk/sdk.py
margin_strategy_sdk-0.0.11.dist-info/LICENSE
margin_strategy_sdk-0.0.11.dist-info/METADATA
margin_strategy_sdk-0.0.11.dist-info/WHEEL
margin_strategy_sdk-0.0.11.dist-info/top_level.txt
margin_strategy_sdk-0.0.11.dist-info/RECORD
