Metadata-Version: 2.1
Name: margin-strategy-sdk
Version: 0.0.11
Summary: Margin Strategy Editor SDK
Home-page: https://github.com/MarginOpenSource/strategy-sdk
Author: Margin UG
Author-email: contact@margin.io
License: UNKNOWN
Platform: UNKNOWN
Classifier: Programming Language :: Python :: 3
Classifier: License :: OSI Approved :: MIT License
Classifier: Operating System :: OS Independent
Requires-Python: >=3.6
License-File: LICENSE
